marinabox/__init__.py
marinabox/api.py
marinabox/cli.py
marinabox/cloud_cli.py
marinabox/cloud_manager.py
marinabox/config.py
marinabox/langgraph.py
marinabox/local_cli.py
marinabox/local_manager.py
marinabox/models.py
marinabox/sdk.py
marinabox/server.py
marinabox/computer_use/__init__.py
marinabox/computer_use/cli.py
marinabox/computer_use/loop.py
marinabox/computer_use/tools/__init__.py
marinabox/computer_use/tools/base.py
marinabox/computer_use/tools/bash.py
marinabox/computer_use/tools/collection.py
marinabox/computer_use/tools/computer.py
marinabox/computer_use/tools/edit.py
marinabox/computer_use/tools/run.py
marinabox-0.1.7.dist-info/LICENSE
marinabox-0.1.7.dist-info/METADATA
marinabox-0.1.7.dist-info/WHEEL
marinabox-0.1.7.dist-info/entry_points.txt
marinabox-0.1.7.dist-info/top_level.txt
marinabox-0.1.7.dist-info/RECORD
