Metadata-Version: 2.1
Name: marinabox
Version: 0.1.7
Summary: An open-source toolkit for deploying containerized desktops and browsers tailored for AI agents
Home-page: https://github.com/bayllama/marinabox
Author: bayllama
Classifier: Programming Language :: Python :: 3
Classifier: License :: OSI Approved :: MIT License
Classifier: Operating System :: OS Independent
Requires-Python: >=3.12
License-File: LICENSE
Requires-Dist: docker
Requires-Dist: requests
Requires-Dist: fastapi
Requires-Dist: uvicorn
Requires-Dist: click
Requires-Dist: boto3
Requires-Dist: streamlit >=1.38.0
Requires-Dist: anthropic[bedrock,vertex] >=0.37.1
Requires-Dist: jsonschema ==4.22.0
Requires-Dist: google-auth <3,>=2
Requires-Dist: pytest ==8.3.3
Requires-Dist: pytest-asyncio ==0.23.6
Requires-Dist: langgraph ==0.2.60
Requires-Dist: langchain-anthropic ==0.3.1
Requires-Dist: langchain-openai ==0.2.2
Requires-Dist: langchain-core ==0.3.28
